sql_assignment_generator/__init__.py
sql_assignment_generator/difficulty_level.py
sql_assignment_generator/domains.py
sql_assignment_generator/query_sintax.py
sql_assignment_generator/sql_errors_details.py
sql_assignment_generator/assignments/__init__.py
sql_assignment_generator/assignments/assignment.py
sql_assignment_generator/assignments/dataset.py
sql_assignment_generator/assignments/exercise.py
sql_assignment_generator/constraints/__init__.py
sql_assignment_generator/constraints/base.py
sql_assignment_generator/constraints/query.py
sql_assignment_generator/constraints/schema.py
sql_assignment_generator/llm/__init__.py
sql_assignment_generator/llm/chatgpt.py
sql_assignment_generator/llm/message.py
sql_assignment_generator/llm/models.py
sql_assignment_generator-0.0.10.dist-info/METADATA
sql_assignment_generator-0.0.10.dist-info/WHEEL
sql_assignment_generator-0.0.10.dist-info/licenses/LICENSE
sql_assignment_generator-0.0.10.dist-info/RECORD
