Metadata-Version: 2.4
Name: sql_assignment_generator
Version: 0.0.10
Summary: This project generates SQL assignments based on common mistakes made by learners.
Project-URL: Repository, https://github.com/DavidePonzini/sql_assignment_generator
Project-URL: Documentation, https://sql-assignment-generator.readthedocs.io/en/latest/index.html
Project-URL: Bug Tracker, https://github.com/DavidePonzini/sql_assignment_generator/issues
Author-email: Davide Ponzini <davide.ponzini95@gmail.com>
License-File: LICENSE
Classifier: License :: OSI Approved :: MIT License
Classifier: Operating System :: OS Independent
Classifier: Programming Language :: Python :: 3
Requires-Python: >=3.11
Requires-Dist: dotenv
Requires-Dist: pydantic
Requires-Dist: sql-error-categorizer>=0.1.10
